setup.cfg
setup.py
torethink/__init__.py
torethink/initiator.py
torethink/torethink.py
torethink.egg-info/PKG-INFO
torethink.egg-info/SOURCES.txt
torethink.egg-info/dependency_links.txt
torethink.egg-info/requires.txt
torethink.egg-info/top_level.txt